md2json/__init__.py
md2json/version.py
md2json-0.0.1.dist-info/LICENSE
md2json-0.0.1.dist-info/METADATA
md2json-0.0.1.dist-info/WHEEL
md2json-0.0.1.dist-info/top_level.txt
md2json-0.0.1.dist-info/RECORD
