Metadata-Version: 2.1
Name: md2json
Version: 0.0.1
Summary: md2json: md2json and json2md
Home-page: https://github.com/bugout-dev/md2json
Author: Neeraj Kashyap
Author-email: neeraj@bugout.dev
License: UNKNOWN
Platform: UNKNOWN
Classifier: Development Status :: 2 - Pre-Alpha
Classifier: Programming Language :: Python
Requires-Dist: mistune (>=2.0.0rc1)
Provides-Extra: dev
Requires-Dist: black ; extra == 'dev'
Requires-Dist: mypy ; extra == 'dev'
Requires-Dist: setuptools ; extra == 'dev'
Requires-Dist: wheel ; extra == 'dev'
Provides-Extra: distribute
Requires-Dist: twine ; extra == 'distribute'
